bioquest/._.DS_Store
bioquest/LICENSE
bioquest/__init__.py
bioquest/_data/._.DS_Store
bioquest/_data/._dre.csv.gz
bioquest/_data/._hsa.csv.gz
bioquest/_data/._mmu.csv.gz
bioquest/_data/._rno.csv.gz
bioquest/_data/__init__.py
bioquest/_data/dre.csv.gz
bioquest/_data/hsa.csv.gz
bioquest/_data/mmu.csv.gz
bioquest/_data/rno.csv.gz
bioquest/ml/.__ml.py
bioquest/ml/__init__.py
bioquest/ml/_ml.py
bioquest/pl/.__palette.py
bioquest/pl/__init__.py
bioquest/pl/_palette.py
bioquest/pl/forest.py
bioquest/st/__init__.py
bioquest/st/_stringpy.py
bioquest/tl/.__IO.py
bioquest/tl/.___init__.py
bioquest/tl/._gene.py
bioquest/tl/_IO.py
bioquest/tl/__init__.py
bioquest/tl/_frame.py
bioquest/tl/gene.py
bioquest/tl/utils.py
bioquest-1.0.4.dist-info/METADATA
bioquest-1.0.4.dist-info/WHEEL
bioquest-1.0.4.dist-info/RECORD
